LICENSE.txt
README.md
requirements.txt
setup.py
image_dl/__init__.py
image_dl/main.py
image_dl.egg-info/PKG-INFO
image_dl.egg-info/SOURCES.txt
image_dl.egg-info/dependency_links.txt
image_dl.egg-info/top_level.txt